{"surahDetails":{"id":84,"arabicName":"الانشقاق","banglaName":"খণ্ড-বিখণ্ডকরণ","englishName":"The Splitting Open","enTranslatedName":"Al-Inshiqaq","arLocation":"مكية","enLocation":"meccan","audio":"https://cdn.islamic.network/quran/audio-surah/128/ar.alafasy/84.mp3","totalAyah":25},"surah":{"id":84,"verses":[{"id":1,"arabic_text":"إِذَا ٱلسَّمَآءُ ٱنشَقَّتۡ","bangl_text":"যখন আকাশ বিদীর্ণ হবে","english_text":"When the sky has split [open]","page":589,"is_sajdah_ayat":false,"audio":"https://cdn.islamic.network/quran/audio/128/ar.alafasy/5885.mp3","colorText":"إِذَا [h:14351[ٱ][l[ل]سَّم[o[َا]ٓءُ [h:14390[ٱ][f:14391[نش]َقَّتْ","juz":30,"ruku":526,"manzil":7,"htmlColorText":"إِذَا <span class=ham_wasl>ٱ</span><span class=laam_shamsiyah>ل</span>سَّم<span class=madda_obligatory>َا</span>ٓءُ <span class=ham_wasl>ٱ</span><span class=ikhafa>نش</span>َقَّتْ <span class=end>١</span>"},{"id":2,"arabic_text":"وَأَذِنَتۡ لِرَبِّهَا وَحُقَّتۡ","bangl_text":"ও তার পালনকর্তার আদেশ পালন করবে এবং আকাশ এরই উপযুক্ত","english_text":"And has responded to its Lord and was obligated [to do so]","page":589,"is_sajdah_ayat":false,"audio":"https://cdn.islamic.network/quran/audio/128/ar.alafasy/5886.mp3","colorText":"وَأَذِنَتْ لِرَبِّهَا وَحُقَّتْ","juz":30,"ruku":526,"manzil":7,"htmlColorText":"وَأَذِنَتْ لِرَبِّهَا وَحُقَّتْ <span class=end>٢</span>"},{"id":3,"arabic_text":"وَإِذَا ٱلۡأَرۡضُ مُدَّتۡ","bangl_text":"এবং যখন পৃথিবীকে সম্প্রসারিত করা হবে।","english_text":"And when the earth has been extended","page":589,"is_sajdah_ayat":false,"audio":"https://cdn.islamic.network/quran/audio/128/ar.alafasy/5887.mp3","colorText":"وَإِذَا [h:14392[ٱ]لْأَرْضُ مُدَّتْ","juz":30,"ruku":526,"manzil":7,"htmlColorText":"وَإِذَا <span class=ham_wasl>ٱ</span>لْأَرْضُ مُدَّتْ <span class=end>٣</span>"},{"id":4,"arabic_text":"وَأَلۡقَتۡ مَا فِيهَا وَتَخَلَّتۡ","bangl_text":"এবং পৃথিবী তার গর্ভস্থিত সবকিছু বাইরে নিক্ষেপ করবে ও শুন্যগর্ভ হয়ে যাবে।","english_text":"And has cast out that within it and relinquished [it]","page":589,"is_sajdah_ayat":false,"audio":"https://cdn.islamic.network/quran/audio/128/ar.alafasy/5888.mp3","colorText":"وَأَلْقَتْ مَا فِيهَا وَتَخَلَّتْ","juz":30,"ruku":526,"manzil":7,"htmlColorText":"وَأَلْقَتْ مَا فِيهَا وَتَخَلَّتْ <span class=end>٤</span>"},{"id":5,"arabic_text":"وَأَذِنَتۡ لِرَبِّهَا وَحُقَّتۡ","bangl_text":"এবং তার পালনকর্তার আদেশ পালন করবে এবং পৃথিবী এরই উপযুক্ত।","english_text":"And has responded to its Lord and was obligated [to do so]","page":589,"is_sajdah_ayat":false,"audio":"https://cdn.islamic.network/quran/audio/128/ar.alafasy/5889.mp3","colorText":"وَأَذِنَتْ لِرَبِّهَا وَحُقَّتْ","juz":30,"ruku":526,"manzil":7,"htmlColorText":"وَأَذِنَتْ لِرَبِّهَا وَحُقَّتْ <span class=end>٥</span>"},{"id":6,"arabic_text":"يَـٰٓأَيُّهَا ٱلۡإِنسَٰنُ إِنَّكَ كَادِحٌ إِلَىٰ رَبِّكَ كَدۡحٗا فَمُلَٰقِيهِ","bangl_text":"হে মানুষ, তোমাকে তোমরা পালনকর্তা পর্যন্ত পৌছতে কষ্ট স্বীকার করতে হবে, অতঃপর তার সাক্ষাৎ ঘটবে।","english_text":"O mankind, indeed you are laboring toward your Lord with [great] exertion and will meet it","page":589,"is_sajdah_ayat":false,"audio":"https://cdn.islamic.network/quran/audio/128/ar.alafasy/5890.mp3","colorText":"يَ[o[ـٰٓ]أَيُّهَا [h:14358[ٱ]لْإِ[f:2732[نس]َ[n[ـٰ]نُ إِ[g[نّ]َكَ كَادِحٌ إِلَىٰ رَبِّكَ كَ[q:14393[دْ][f:14394[حًا ف]َمُلَ[n[ـٰ]ق[p[ِي]هِ","juz":30,"ruku":526,"manzil":7,"htmlColorText":"يَ<span class=madda_obligatory>ـٰٓ</span>أَيُّهَا <span class=ham_wasl>ٱ</span>لْإِ<span class=ikhafa>نس</span>َ<span class=madda_normal>ـٰ</span>نُ إِ<span class=ghunnah>نّ</span>َكَ كَادِحٌ إِلَىٰ رَبِّكَ كَ<span class=qalaqah>دْ</span><span class=ikhafa>حًا ف</span>َمُلَ<span class=madda_normal>ـٰ</span>ق<span class=madda_permissible>ِي</span>هِ <span class=end>٦</span>"},{"id":7,"arabic_text":"فَأَمَّا مَنۡ أُوتِيَ كِتَٰبَهُۥ بِيَمِينِهِۦ","bangl_text":"যাকে তার আমলনামা ডান হাতে দেয়া হবে","english_text":"Then as for he who is given his record in his right hand","page":589,"is_sajdah_ayat":false,"audio":"https://cdn.islamic.network/quran/audio/128/ar.alafasy/5891.mp3","colorText":"فَأَ[g[مّ]َا مَنْ أُوتِىَ كِتَ[n[ـٰ]بَهُ[n[ۥ] بِيَمِينِهِۦ","juz":30,"ruku":526,"manzil":7,"htmlColorText":"فَأَ<span class=ghunnah>مّ</span>َا مَنْ أُوتِىَ كِتَ<span class=madda_normal>ـٰ</span>بَهُ<span class=madda_normal>ۥ</span> بِيَمِينِهِۦ <span class=end>٧</span>"},{"id":8,"arabic_text":"فَسَوۡفَ يُحَاسَبُ حِسَابٗا يَسِيرٗا","bangl_text":"তার হিসাব-নিকাশ সহজে হয়ে যাবে","english_text":"He will be judged with an easy account","page":589,"is_sajdah_ayat":false,"audio":"https://cdn.islamic.network/quran/audio/128/ar.alafasy/5892.mp3","colorText":"فَسَوْفَ يُحَاسَبُ حِسَا[a:14395[بًا ي]َسِيرًا","juz":30,"ruku":526,"manzil":7,"htmlColorText":"فَسَوْفَ يُحَاسَبُ حِسَا<span class=idgham_ghunnah>بًا ي</span>َسِيرًا <span class=end>٨</span>"},{"id":9,"arabic_text":"وَيَنقَلِبُ إِلَىٰٓ أَهۡلِهِۦ مَسۡرُورٗا","bangl_text":"এবং সে তার পরিবার-পরিজনের কাছে হৃষ্টচিত্তে ফিরে যাবে","english_text":"And return to his people in happiness","page":589,"is_sajdah_ayat":false,"audio":"https://cdn.islamic.network/quran/audio/128/ar.alafasy/5893.mp3","colorText":"وَيَ[f:14396[نق]َلِبُ إِلَ[o[ىٰٓ] أَهْلِه[n[ِۦ] مَسْرُورًا","juz":30,"ruku":526,"manzil":7,"htmlColorText":"وَيَ<span class=ikhafa>نق</span>َلِبُ إِلَ<span class=madda_obligatory>ىٰٓ</span> أَهْلِه<span class=madda_normal>ِۦ</span> مَسْرُورًا <span class=end>٩</span>"},{"id":10,"arabic_text":"وَأَمَّا مَنۡ أُوتِيَ كِتَٰبَهُۥ وَرَآءَ ظَهۡرِهِۦ","bangl_text":"এবং যাকে তার আমলনামা পিঠের পশ্চাদ্দিক থেকে দেয়া, হবে","english_text":"But as for he who is given his record behind his back","page":589,"is_sajdah_ayat":false,"audio":"https://cdn.islamic.network/quran/audio/128/ar.alafasy/5894.mp3","colorText":"وَأَ[g[مّ]َا مَنْ أُوتِىَ كِتَ[n[ـٰ]بَهُ[n[ۥ] وَر[o[َا]ٓءَ ظَهْرِهِۦ","juz":30,"ruku":526,"manzil":7,"htmlColorText":"وَأَ<span class=ghunnah>مّ</span>َا مَنْ أُوتِىَ كِتَ<span class=madda_normal>ـٰ</span>بَهُ<span class=madda_normal>ۥ</span> وَر<span class=madda_obligatory>َا</span>ٓءَ ظَهْرِهِۦ <span class=end>١٠</span>"},{"id":11,"arabic_text":"فَسَوۡفَ يَدۡعُواْ ثُبُورٗا","bangl_text":"সে মৃত্যুকে আহবান করবে","english_text":"He will cry out for destruction","page":589,"is_sajdah_ayat":false,"audio":"https://cdn.islamic.network/quran/audio/128/ar.alafasy/5895.mp3","colorText":"فَسَوْفَ يَ[q:1242[دْ]عُو[s[اْ] ثُبُورًا","juz":30,"ruku":526,"manzil":7,"htmlColorText":"فَسَوْفَ يَ<span class=qalaqah>دْ</span>عُو<span class=slnt>اْ</span> ثُبُورًا <span class=end>١١</span>"},{"id":12,"arabic_text":"وَيَصۡلَىٰ سَعِيرًا","bangl_text":"এবং জাহান্নামে প্রবেশ করবে।","english_text":"And [enter to] burn in a Blaze","page":589,"is_sajdah_ayat":false,"audio":"https://cdn.islamic.network/quran/audio/128/ar.alafasy/5896.mp3","colorText":"وَيَصْلَىٰ سَعِيرًا","juz":30,"ruku":526,"manzil":7,"htmlColorText":"وَيَصْلَىٰ سَعِيرًا <span class=end>١٢</span>"},{"id":13,"arabic_text":"إِنَّهُۥ كَانَ فِيٓ أَهۡلِهِۦ مَسۡرُورًا","bangl_text":"সে তার পরিবার-পরিজনের মধ্যে আনন্দিত ছিল।","english_text":"Indeed, he had [once] been among his people in happiness","page":589,"is_sajdah_ayat":false,"audio":"https://cdn.islamic.network/quran/audio/128/ar.alafasy/5897.mp3","colorText":"إِ[g[نّ]َهُ[n[ۥ] كَانَ ف[o[ِىٓ] أَهْلِه[n[ِۦ] مَسْرُورًا","juz":30,"ruku":526,"manzil":7,"htmlColorText":"إِ<span class=ghunnah>نّ</span>َهُ<span class=madda_normal>ۥ</span> كَانَ ف<span class=madda_obligatory>ِىٓ</span> أَهْلِه<span class=madda_normal>ِۦ</span> مَسْرُورًا <span class=end>١٣</span>"},{"id":14,"arabic_text":"إِنَّهُۥ ظَنَّ أَن لَّن يَحُورَ","bangl_text":"সে মনে করত যে, সে কখনও ফিরে যাবে না।","english_text":"Indeed, he had thought he would never return [to Allah]","page":589,"is_sajdah_ayat":false,"audio":"https://cdn.islamic.network/quran/audio/128/ar.alafasy/5898.mp3","colorText":"إِ[g[نّ]َهُ[n[ۥ] ظَ[g[نّ]َ أ[u:8842[َن ل]ّ[a:14397[َن ي]َح[p[ُو]رَ","juz":30,"ruku":526,"manzil":7,"htmlColorText":"إِ<span class=ghunnah>نّ</span>َهُ<span class=madda_normal>ۥ</span> ظَ<span class=ghunnah>نّ</span>َ أ<span class=idgham_wo_ghunnah>َن ل</span>ّ<span class=idgham_ghunnah>َن ي</span>َح<span class=madda_permissible>ُو</span>رَ <span class=end>١٤</span>"},{"id":15,"arabic_text":"بَلَىٰٓۚ إِنَّ رَبَّهُۥ كَانَ بِهِۦ بَصِيرٗا","bangl_text":"কেন যাবে না, তার পালনকর্তা তো তাকে দেখতেন।","english_text":"But yes! Indeed, his Lord was ever of him, Seeing","page":589,"is_sajdah_ayat":false,"audio":"https://cdn.islamic.network/quran/audio/128/ar.alafasy/5899.mp3","colorText":"بَلَ[o[ىٰٓ] إِ[g[نّ]َ رَبَّهُ[n[ۥ] كَانَ بِه[n[ِۦ] بَصِيرًا","juz":30,"ruku":526,"manzil":7,"htmlColorText":"بَلَ<span class=madda_obligatory>ىٰٓ</span> إِ<span class=ghunnah>نّ</span>َ رَبَّهُ<span class=madda_normal>ۥ</span> كَانَ بِه<span class=madda_normal>ِۦ</span> بَصِيرًا <span class=end>١٥</span>"},{"id":16,"arabic_text":"فَلَآ أُقۡسِمُ بِٱلشَّفَقِ","bangl_text":"আমি শপথ করি সন্ধ্যাকালীন লাল আভার","english_text":"So I swear by the twilight glow","page":589,"is_sajdah_ayat":false,"audio":"https://cdn.islamic.network/quran/audio/128/ar.alafasy/5900.mp3","colorText":"فَل[o[َآ] أُ[q:13287[قْ]سِمُ بِ[h:14398[ٱ][l[ل]شَّفَ[q[ق]ِ","juz":30,"ruku":526,"manzil":7,"htmlColorText":"فَل<span class=madda_obligatory>َآ</span> أُ<span class=qalaqah>قْ</span>سِمُ بِ<span class=ham_wasl>ٱ</span><span class=laam_shamsiyah>ل</span>شَّفَ<span class=qalaqah>ق</span>ِ <span class=end>١٦</span>"},{"id":17,"arabic_text":"وَٱلَّيۡلِ وَمَا وَسَقَ","bangl_text":"এবং রাত্রির, এবং তাতে যার সমাবেশ ঘটে","english_text":"And [by] the night and what it envelops","page":589,"is_sajdah_ayat":false,"audio":"https://cdn.islamic.network/quran/audio/128/ar.alafasy/5901.mp3","colorText":"وَ[h:9999[ٱ]لَّيْلِ وَمَا وَسَ[q[ق]َ","juz":30,"ruku":526,"manzil":7,"htmlColorText":"وَ<span class=ham_wasl>ٱ</span>لَّيْلِ وَمَا وَسَ<span class=qalaqah>ق</span>َ <span class=end>١٧</span>"},{"id":18,"arabic_text":"وَٱلۡقَمَرِ إِذَا ٱتَّسَقَ","bangl_text":"এবং চন্দ্রের, যখন তা পূর্ণরূপ লাভ করে","english_text":"And [by] the moon when it becomes full","page":589,"is_sajdah_ayat":false,"audio":"https://cdn.islamic.network/quran/audio/128/ar.alafasy/5902.mp3","colorText":"وَ[h:9999[ٱ]لْقَمَرِ إِذَا [h:14399[ٱ]تَّسَ[q[ق]َ","juz":30,"ruku":526,"manzil":7,"htmlColorText":"وَ<span class=ham_wasl>ٱ</span>لْقَمَرِ إِذَا <span class=ham_wasl>ٱ</span>تَّسَ<span class=qalaqah>ق</span>َ <span class=end>١٨</span>"},{"id":19,"arabic_text":"لَتَرۡكَبُنَّ طَبَقًا عَن طَبَقٖ","bangl_text":"নিশ্চয় তোমরা এক সিঁড়ি থেকে আরেক সিঁড়িতে আরোহণ করবে।","english_text":"[That] you will surely experience state after state","page":589,"is_sajdah_ayat":false,"audio":"https://cdn.islamic.network/quran/audio/128/ar.alafasy/5903.mp3","colorText":"لَتَرْكَبُ[g[نّ]َ طَبَقًا عَ[f:14400[ن ط]َبَ[q[ق]ٍ","juz":30,"ruku":526,"manzil":7,"htmlColorText":"لَتَرْكَبُ<span class=ghunnah>نّ</span>َ طَبَقًا عَ<span class=ikhafa>ن ط</span>َبَ<span class=qalaqah>ق</span>ٍ <span class=end>١٩</span>"},{"id":20,"arabic_text":"فَمَا لَهُمۡ لَا يُؤۡمِنُونَ","bangl_text":"অতএব, তাদের কি হল যে, তারা ঈমান আনে না","english_text":"So what is [the matter] with them [that] they do not believe","page":589,"is_sajdah_ayat":false,"audio":"https://cdn.islamic.network/quran/audio/128/ar.alafasy/5904.mp3","colorText":"فَمَا لَهُمْ لَا يُؤْمِن[p[ُو]نَ","juz":30,"ruku":526,"manzil":7,"htmlColorText":"فَمَا لَهُمْ لَا يُؤْمِن<span class=madda_permissible>ُو</span>نَ <span class=end>٢٠</span>"},{"id":21,"arabic_text":"وَإِذَا قُرِئَ عَلَيۡهِمُ ٱلۡقُرۡءَانُ لَا يَسۡجُدُونَۤ۩","bangl_text":"যখন তাদের কাছে কোরআন পাঠ করা হয়, তখন সেজদা করে না।","english_text":"And when the Qur'an is recited to them, they do not prostrate [to Allah]","page":589,"is_sajdah_ayat":true,"audio":"https://cdn.islamic.network/quran/audio/128/ar.alafasy/5905.mp3","colorText":"وَإِذَا قُرِئَ عَلَيْهِمُ [h:14401[ٱ]لْقُرْءَانُ لَا يَسْجُدُ[p[و]نَ ۩","juz":30,"ruku":526,"manzil":7,"htmlColorText":"وَإِذَا قُرِئَ عَلَيْهِمُ <span class=ham_wasl>ٱ</span>لْقُرْءَانُ لَا يَسْجُدُ<span class=madda_permissible>و</span>نَ ۩ <span class=end>٢١</span>"},{"id":22,"arabic_text":"بَلِ ٱلَّذِينَ كَفَرُواْ يُكَذِّبُونَ","bangl_text":"বরং কাফেররা এর প্রতি মিথ্যারোপ করে।","english_text":"But those who have disbelieved deny","page":589,"is_sajdah_ayat":false,"audio":"https://cdn.islamic.network/quran/audio/128/ar.alafasy/5906.mp3","colorText":"بَلِ [h:10932[ٱ]لَّذِينَ كَفَرُو[s[اْ] يُكَذِّب[p[ُو]نَ","juz":30,"ruku":526,"manzil":7,"htmlColorText":"بَلِ <span class=ham_wasl>ٱ</span>لَّذِينَ كَفَرُو<span class=slnt>اْ</span> يُكَذِّب<span class=madda_permissible>ُو</span>نَ <span class=end>٢٢</span>"},{"id":23,"arabic_text":"وَٱللَّهُ أَعۡلَمُ بِمَا يُوعُونَ","bangl_text":"তারা যা সংরক্ষণ করে, আল্লাহ তা জানেন।","english_text":"And Allah is most knowing of what they keep within themselves","page":589,"is_sajdah_ayat":false,"audio":"https://cdn.islamic.network/quran/audio/128/ar.alafasy/5907.mp3","colorText":"وَ[h:9999[ٱ]للَّهُ أَعْلَمُ بِمَا يُوع[p[ُو]نَ","juz":30,"ruku":526,"manzil":7,"htmlColorText":"وَ<span class=ham_wasl>ٱ</span>للَّهُ أَعْلَمُ بِمَا يُوع<span class=madda_permissible>ُو</span>نَ <span class=end>٢٣</span>"},{"id":24,"arabic_text":"فَبَشِّرۡهُم بِعَذَابٍ أَلِيمٍ","bangl_text":"অতএব, তাদেরকে যন্ত্রণাদায়ক শাস্তির সুসংবাদ দিন।","english_text":"So give them tidings of a painful punishment","page":589,"is_sajdah_ayat":false,"audio":"https://cdn.islamic.network/quran/audio/128/ar.alafasy/5908.mp3","colorText":"فَبَشِّرْه[c:1811[ُم ب]ِعَذَابٍ أَل[p[ِي]مٍ","juz":30,"ruku":526,"manzil":7,"htmlColorText":"فَبَشِّرْه<span class=ikhafa_shafawi>ُم ب</span>ِعَذَابٍ أَل<span class=madda_permissible>ِي</span>مٍ <span class=end>٢٤</span>"},{"id":25,"arabic_text":"إِلَّا ٱلَّذِينَ ءَامَنُواْ وَعَمِلُواْ ٱلصَّـٰلِحَٰتِ لَهُمۡ أَجۡرٌ غَيۡرُ مَمۡنُونِۭ","bangl_text":"কিন্তু যারা বিশ্বাস স্থাপন করে ও সৎকর্ম করে, তাদের জন্য রয়েছে অফুরন্ত পুরস্কার।","english_text":"Except for those who believe and do righteous deeds. For them is a reward uninterrupted","page":589,"is_sajdah_ayat":false,"audio":"https://cdn.islamic.network/quran/audio/128/ar.alafasy/5909.mp3","colorText":"إِلَّا [h:778[ٱ]لَّذِينَ ءَامَنُو[s[اْ] وَعَمِلُو[s[اْ] [h:118[ٱ][l[ل]صَّ[n[ـٰ]لِحَ[n[ـٰ]تِ لَهُمْ أَ[q:2423[جْ]رٌ غَيْرُ مَمْن[p[ُو]نِۭ","juz":30,"ruku":526,"manzil":7,"htmlColorText":"إِلَّا <span class=ham_wasl>ٱ</span>لَّذِينَ ءَامَنُو<span class=slnt>اْ</span> وَعَمِلُو<span class=slnt>اْ</span> <span class=ham_wasl>ٱ</span><span class=laam_shamsiyah>ل</span>صَّ<span class=madda_normal>ـٰ</span>لِحَ<span class=madda_normal>ـٰ</span>تِ لَهُمْ أَ<span class=qalaqah>جْ</span>رٌ غَيْرُ مَمْن<span class=madda_permissible>ُو</span>نِۭ <span class=end>٢٥</span>"}]}}